sf_convert/__init__.py
sf_convert/command_line/UtilExec.py
sf_convert/command_line/htmlFormExec.py
sf_convert/command_line/main.py
sf_convert/data/dictdata.json
sf_convert/export_dir/__init__.py
sf_convert/export_dir/export_cif.py
sf_convert/export_dir/export_cns.py
sf_convert/export_dir/export_mtz.py
sf_convert/import_dir/__init__.py
sf_convert/import_dir/import_cif.py
sf_convert/import_dir/import_cns.py
sf_convert/import_dir/import_mtz.py
sf_convert/sffile/__init__.py
sf_convert/sffile/get_items_pdb.py
sf_convert/sffile/guess_sf_format.py
sf_convert/sffile/sf_file.py
sf_convert/utils/CheckSfFile.py
sf_convert/utils/CifUtils.py
sf_convert/utils/GenMtzHtml.py
sf_convert/utils/MtzUtils.py
sf_convert/utils/SpaceGroup.py
sf_convert/utils/TextUtils.py
sf_convert/utils/__init__.py
sf_convert/utils/dict_filter.py
sf_convert/utils/pinfo_file.py
sf_convert/utils/reformat_sfhead.py
sf_convert/utils/sf_correct.py
sf_convert/utils/version.py
sf_convert-2.1.13.dist-info/licenses/LICENSE
sf_convert-2.1.13.dist-info/METADATA
sf_convert-2.1.13.dist-info/WHEEL
sf_convert-2.1.13.dist-info/entry_points.txt
sf_convert-2.1.13.dist-info/top_level.txt
sf_convert-2.1.13.dist-info/RECORD
