Metadata-Version: 2.4
Name: sf_convert
Version: 2.1.13
Summary: Package for sf_convert
Author-email: Vivek Reddy Chithari <vivek.chithari@rcsb.org>, Ezra Peisach <ezra.peisach@rcsb.org>
License: apache-2.0
Classifier: Development Status :: 3 - Alpha
Classifier: Programming Language :: Python :: 3
Classifier: Intended Audience :: Developers
Classifier: Natural Language :: English
Classifier: License :: OSI Approved :: Apache Software License
Requires-Python: >=3.6
License-File: LICENSE
Requires-Dist: mmcif~=0.87
Requires-Dist: gemmi
Requires-Dist: numpy
Dynamic: license-file
